pyntagma/__init__.py
pyntagma/agent.py
pyntagma/document.py
pyntagma/pdf_reader.py
pyntagma/position.py
pyntagma-0.0.3.dist-info/METADATA
pyntagma-0.0.3.dist-info/WHEEL
pyntagma-0.0.3.dist-info/entry_points.txt
pyntagma-0.0.3.dist-info/RECORD
