Metadata-Version: 2.4
Name: pyntagma
Version: 0.0.3
Summary: Pyntagma is a Python library for creating and managing complex data structures with ease. Its name is derived from the Greek word 'Syntagma', meaning 'composition', symbolizing that this package fits for semi-structured documents
Author-email: MarcellGranat <granatcellmar98@gmail.com>
Requires-Python: >=3.9
Requires-Dist: pdfplumber>=0.9.0
Requires-Dist: pydantic-ai>=0.8.1
Requires-Dist: pydantic>=2.0.0
Provides-Extra: test
Requires-Dist: pytest-cov>=4.0.0; extra == 'test'
Requires-Dist: pytest>=7.0.0; extra == 'test'
